datasheet_downloader/__init__.py
datasheet_downloader/cli.py
datasheet_downloader/downloader.py
datasheet_downloader-0.1.0.dist-info/METADATA
datasheet_downloader-0.1.0.dist-info/WHEEL
datasheet_downloader-0.1.0.dist-info/entry_points.txt
datasheet_downloader-0.1.0.dist-info/RECORD
