Metadata-Version: 2.3
Name: datasheet-downloader
Version: 0.1.0
Summary: A Python package to search and download electronic component datasheets by MPN
License: MIT
Keywords: datasheet,electronics,components,download,automation
Author: Yange
Author-email: posterscofield@gmail.com
Requires-Python: >=3.11
Classifier: Development Status :: 4 - Beta
Classifier: Intended Audience :: Developers
Classifier: License :: OSI Approved :: MIT License
Classifier: Programming Language :: Python :: 3
Classifier: Programming Language :: Python :: 3.11
Classifier: Programming Language :: Python :: 3.12
Classifier: Topic :: Software Development :: Libraries :: Python Modules
Requires-Dist: beautifulsoup4 (>=4.12.0)
Requires-Dist: pandas (>=2.0.0)
Requires-Dist: playwright (>=1.40.0)
Requires-Dist: pymupdf (>=1.22.0)
Requires-Dist: requests (>=2.31.0)
Requires-Dist: tqdm (>=4.66.0)
